odoo/addons/stock_picking_batch_print_pickings/README.rst
odoo/addons/stock_picking_batch_print_pickings/__init__.py
odoo/addons/stock_picking_batch_print_pickings/__manifest__.py
odoo/addons/stock_picking_batch_print_pickings/i18n/es.po
odoo/addons/stock_picking_batch_print_pickings/i18n/it.po
odoo/addons/stock_picking_batch_print_pickings/i18n/pt_BR.po
odoo/addons/stock_picking_batch_print_pickings/i18n/stock_picking_batch_print_pickings.pot
odoo/addons/stock_picking_batch_print_pickings/migrations/16.0.1.0.3/post-migrate.py
odoo/addons/stock_picking_batch_print_pickings/models/__init__.py
odoo/addons/stock_picking_batch_print_pickings/models/stock_picking_batch.py
odoo/addons/stock_picking_batch_print_pickings/models/stock_picking_type.py
odoo/addons/stock_picking_batch_print_pickings/readme/CONFIGURE.md
odoo/addons/stock_picking_batch_print_pickings/readme/CONTEXT.md
odoo/addons/stock_picking_batch_print_pickings/readme/CONTRIBUTORS.md
odoo/addons/stock_picking_batch_print_pickings/readme/DESCRIPTION.md
odoo/addons/stock_picking_batch_print_pickings/readme/USAGE.md
odoo/addons/stock_picking_batch_print_pickings/report/stock_picking_batch_print_pickings_report.xml
odoo/addons/stock_picking_batch_print_pickings/static/description/icon.png
odoo/addons/stock_picking_batch_print_pickings/static/description/index.html
odoo/addons/stock_picking_batch_print_pickings/tests/__init__.py
odoo/addons/stock_picking_batch_print_pickings/tests/test_batch_print_pickings.py
odoo/addons/stock_picking_batch_print_pickings/views/report_picking_batch_print_pickings.xml
odoo/addons/stock_picking_batch_print_pickings/views/stock_picking_batch_views.xml
odoo/addons/stock_picking_batch_print_pickings/views/stock_picking_type_views.xml
odoo_addon_stock_picking_batch_print_pickings-18.0.1.0.1.3.dist-info/METADATA
odoo_addon_stock_picking_batch_print_pickings-18.0.1.0.1.3.dist-info/WHEEL
odoo_addon_stock_picking_batch_print_pickings-18.0.1.0.1.3.dist-info/top_level.txt
odoo_addon_stock_picking_batch_print_pickings-18.0.1.0.1.3.dist-info/RECORD
